odoo10_addon_l10n_br_generic-10.0.1.0.0.99.dev7-nspkg.pth
odoo/addons/l10n_br_generic/README.rst
odoo/addons/l10n_br_generic/__init__.py
odoo/addons/l10n_br_generic/__manifest__.py
odoo/addons/l10n_br_generic/data/account.account.template.csv
odoo/addons/l10n_br_generic/data/account_chart_template_data.yml
odoo/addons/l10n_br_generic/data/account_tax_group_data.xml
odoo/addons/l10n_br_generic/data/account_tax_template_data.xml
odoo/addons/l10n_br_generic/data/l10n_br_chart_data.xml
odoo/addons/l10n_br_generic/i18n/l10n_br_generic.pot
odoo/addons/l10n_br_generic/models/__init__.py
odoo/addons/l10n_br_generic/models/account_tax.py
odoo/addons/l10n_br_generic/models/account_tax_group.py
odoo/addons/l10n_br_generic/models/account_tax_template.py
odoo/addons/l10n_br_generic/static/description/icon.png
odoo/addons/l10n_br_generic/views/account_view.xml
odoo10_addon_l10n_br_generic-10.0.1.0.0.99.dev7.dist-info/METADATA
odoo10_addon_l10n_br_generic-10.0.1.0.0.99.dev7.dist-info/WHEEL
odoo10_addon_l10n_br_generic-10.0.1.0.0.99.dev7.dist-info/namespace_packages.txt
odoo10_addon_l10n_br_generic-10.0.1.0.0.99.dev7.dist-info/top_level.txt
odoo10_addon_l10n_br_generic-10.0.1.0.0.99.dev7.dist-info/RECORD
